src/__init__.py
src/palmers_preprocessing/__init__.py
src/palmers_preprocessing/clearml_data_handler.py
src/palmers_preprocessing/config.py
src/palmers_preprocessing/events_handler.py
src/palmers_preprocessing/lags_feature_handler.py
src/palmers_preprocessing/preprocessor.py
src/palmers_preprocessing/regular_data_handler.py
src/palmers_preprocessing/utils.py
src/palmers_preprocessing/features/__init__.py
src/palmers_preprocessing/features/config.py
src/palmers_preprocessing/features/cumulative_features.py
src/palmers_preprocessing/features/event_features.py
src/palmers_preprocessing/features/future_features.py
src/palmers_preprocessing/features/lags_features.py
src/palmers_preprocessing/features/weather_features.py
src/palmers_preprocessing/tests/__init__.py
src/palmers_preprocessing/tests/config_batch_dict.py
src/palmers_preprocessing/tests/event_feature_test.py
src/palmers_preprocessing/tests/features_test.py
src/palmers_preprocessing/tests/lags_features_test.py
src/palmers_preprocessing/tests/preprocessor_test.py
src/palmers_preprocessing/tests/sanity_checks.py
src/palmers_preprocessing/tests/test_todelete.py
src/palmers_preprocessing/tests/weather_test.py
palmers_preprocess-0.0.17.dist-info/METADATA
palmers_preprocess-0.0.17.dist-info/WHEEL
palmers_preprocess-0.0.17.dist-info/licenses/LICENSE
palmers_preprocess-0.0.17.dist-info/RECORD
